my_model_package/__init__.py
my_model_package/model.py
ADE_Model-0.1.0.dist-info/METADATA
ADE_Model-0.1.0.dist-info/WHEEL
ADE_Model-0.1.0.dist-info/top_level.txt
ADE_Model-0.1.0.dist-info/RECORD
