Metadata-Version: 2.1
Name: ADE_Model
Version: 0.1.0
Summary: ADE Detection Model for Adverse Drug Events
Home-page: https://github.com/heetbhuva1801/ADE_Model.git
Author: Heet Bhuva
Author-email: heetbhuva18@gmail.com
Classifier: Programming Language :: Python :: 3
Classifier: License :: OSI Approved :: MIT License
Classifier: Operating System :: OS Independent
Requires-Python: >=3.6
Requires-Dist: tensorflow>=2.0
Requires-Dist: transformers>=4.0
